blip_flowanalysis/__init__.py
blip_flowanalysis/abstract/__init__.py
blip_flowanalysis/abstract/analyser.py
blip_flowanalysis/analysis/__init__.py
blip_flowanalysis/analysis/duplicated_paths.py
blip_flowanalysis/analysis/long_script.py
blip_flowanalysis/analysis/missing_trackings.py
blip_flowanalysis/analysis/process_http_return_validation.py
blip_flowanalysis/analysis/comparator/__init__.py
blip_flowanalysis/analysis/comparator/_specific_comparators.py
blip_flowanalysis/analysis/comparator/actions_comparator.py
blip_flowanalysis/analysis/comparator/conditions_comparator.py
blip_flowanalysis/analysis/comparator/interface_comparator.py
blip_flowanalysis/analysis/comparator/outputs_comparator.py
blip_flowanalysis/analysis/comparator/states_comparator.py
blip_flowanalysis/analysis/variable_finder/__init__.py
blip_flowanalysis/analysis/variable_finder/_specific_variable_finders.py
blip_flowanalysis/analysis/variable_finder/action_variable_finder.py
blip_flowanalysis/analysis/variable_finder/interface_variable_finder.py
blip_flowanalysis/analysis/variable_finder/output_variable_finder.py
blip_flowanalysis/analysis/variable_finder/state_variable_finder.py
blip_flowanalysis/core/__init__.py
blip_flowanalysis/core/flow.py
blip_flowanalysis/errors/__init__.py
blip_flowanalysis/errors/flow_error.py
blip_flowanalysis/errors/long_script_error.py
blip_flowanalysis/utils/__init__.py
tests/analysis/__init__.py
tests/analysis/test_long_script.py
tests/analysis/comparators/__init__.py
tests/analysis/comparators/test_actions_comparator.py
tests/analysis/comparators/test_conditions_comparator.py
tests/analysis/comparators/test_outputs_comparator.py
tests/analysis/comparators/test_specific_comparators.py
tests/analysis/comparators/test_states_comparator.py
blip_flowanalysis-0.6.1.dist-info/LICENSE
blip_flowanalysis-0.6.1.dist-info/METADATA
blip_flowanalysis-0.6.1.dist-info/WHEEL
blip_flowanalysis-0.6.1.dist-info/top_level.txt
blip_flowanalysis-0.6.1.dist-info/RECORD
