Metadata-Version: 2.1
Name: blip-flowanalysis
Version: 0.6.1
Summary: A solution for chatbot constructors to identify problems in flow structure.
Home-page: UNKNOWN
Author: Squad XD
Author-email: anaytics.dar@take.net
Maintainer: daresearch
Maintainer-email: anaytics.dar@take.net
License: MIT License
Keywords: chatbot,flow,analysis
Platform: UNKNOWN
Classifier: Programming Language :: Python :: 3.7
Classifier: Operating System :: OS Independent
Classifier: License :: OSI Approved :: MIT License
Provides-Extra: tests
Requires-Dist: pytest-cov (<3.0,>=2.8.1) ; extra == 'tests'
Requires-Dist: pytest-mock (<2.0,>=1.7.1) ; extra == 'tests'
Requires-Dist: pytest (<4.0,>=3.4) ; extra == 'tests'
